[
  {
    "Condition": {
      "Criterion": [
        {
          "PassRate": 95.0,
          "CriteriaMethod": "num_tp",
          "CriteriaLevel": "hard",
          "Filter": {
            "Distance": [0.0, 50.0]
          }
        },
        {
          "PassRate": 95.0,
          "CriteriaMethod": "num_tp",
          "CriteriaLevel": "easy",
          "Filter": {
            "Distance": [50.0, 1.7976931348623157e308]
          }
        }
      ]
    }
  },
  {
    "Result": {
      "Success": false,
      "Summary": "NoData"
    },
    "Stamp": {
      "System": 1705038407.1164799
    },
    "Frame": {}
  },
  {
    "Result": {
      "Success": false,
      "Summary": "Passed:  criteria0 (Success): 1 / 1 -> 100.00%, Failed:  criteria1 (Fail): 0 / 1 -> 0.00%"
    },
    "Stamp": {
      "System": 1705038422.2768033,
      "ROS": 1686890777.947095
    },
    "Frame": {
      "criteria0": {
        "Filter": {
          "Distance": [0.0, 50.0]
        },
        "Ego": {
          "TransformStamped": {
            "header": {
              "stamp": {
                "sec": 1686890777,
                "nanosec": 450032640
              },
              "frame_id": "map"
            },
            "child_frame_id": "base_link",
            "transform": {
              "translation": {
                "x": 65400.005284654704,
                "y": 684.6110709560425,
                "z": 716.0409713439462
              },
              "rotation": {
                "x": -0.00461444671951176,
                "y": 0.009981555647030226,
                "z": 0.02238773904911126,
                "w": 0.9996888838876857
              }
            },
            "rotation_euler": {
              "roll": -0.008780991289684006,
              "pitch": 0.020164881060876202,
              "yaw": 0.04469339002875218
            }
          }
        },
        "FrameName": "0",
        "FrameSkip": 8,
        "PassFail": {
          "Result": {
            "Total": "Success",
            "Frame": "Success"
          },
          "Info": {
            "TP": 0,
            "FP": 0,
            "FN": 0
          }
        }
      },
      "criteria1": {
        "Filter": {
          "Distance": [50.0, 1.7976931348623157e308]
        },
        "Ego": {
          "TransformStamped": {
            "header": {
              "stamp": {
                "sec": 1686890777,
                "nanosec": 450032640
              },
              "frame_id": "map"
            },
            "child_frame_id": "base_link",
            "transform": {
              "translation": {
                "x": 65400.005284654704,
                "y": 684.6110709560425,
                "z": 716.0409713439462
              },
              "rotation": {
                "x": -0.00461444671951176,
                "y": 0.009981555647030226,
                "z": 0.02238773904911126,
                "w": 0.9996888838876857
              }
            },
            "rotation_euler": {
              "roll": -0.008780991289684006,
              "pitch": 0.020164881060876202,
              "yaw": 0.04469339002875218
            }
          }
        },
        "FrameName": "0",
        "FrameSkip": 8,
        "PassFail": {
          "Result": {
            "Total": "Fail",
            "Frame": "Fail"
          },
          "Info": {
            "TP": 0,
            "FP": 2,
            "FN": 0
          }
        }
      }
    }
  },
  {
    "Result": {
      "Success": false,
      "Summary": "Passed:  criteria0 (Success): 2 / 2 -> 100.00%, Failed:  criteria1 (Fail): 0 / 2 -> 0.00%"
    },
    "Stamp": {
      "System": 1705038422.467463,
      "ROS": 1686890778.0440595
    },
    "Frame": {
      "criteria0": {
        "Filter": {
          "Distance": [0.0, 50.0]
        },
        "Ego": {
          "TransformStamped": {
            "header": {
              "stamp": {
                "sec": 1686890777,
                "nanosec": 550075904
              },
              "frame_id": "map"
            },
            "child_frame_id": "base_link",
            "transform": {
              "translation": {
                "x": 65400.005365192264,
                "y": 684.6110916633601,
                "z": 716.0412860916304
              },
              "rotation": {
                "x": -0.004605063317779468,
                "y": 0.009984572633610607,
                "z": 0.022387759614028332,
                "w": 0.9996888965676411
              }
            },
            "rotation_euler": {
              "roll": -0.008762091366508531,
              "pitch": 0.020170494594658722,
              "yaw": 0.04469359655461036
            }
          }
        },
        "FrameName": "1",
        "FrameSkip": 8,
        "PassFail": {
          "Result": {
            "Total": "Success",
            "Frame": "Success"
          },
          "Info": {
            "TP": 0,
            "FP": 0,
            "FN": 0
          }
        }
      },
      "criteria1": {
        "Filter": {
          "Distance": [50.0, 1.7976931348623157e308]
        },
        "Ego": {
          "TransformStamped": {
            "header": {
              "stamp": {
                "sec": 1686890777,
                "nanosec": 550075904
              },
              "frame_id": "map"
            },
            "child_frame_id": "base_link",
            "transform": {
              "translation": {
                "x": 65400.005365192264,
                "y": 684.6110916633601,
                "z": 716.0412860916304
              },
              "rotation": {
                "x": -0.004605063317779468,
                "y": 0.009984572633610607,
                "z": 0.022387759614028332,
                "w": 0.9996888965676411
              }
            },
            "rotation_euler": {
              "roll": -0.008762091366508531,
              "pitch": 0.020170494594658722,
              "yaw": 0.04469359655461036
            }
          }
        },
        "FrameName": "1",
        "FrameSkip": 8,
        "PassFail": {
          "Result": {
            "Total": "Fail",
            "Frame": "Fail"
          },
          "Info": {
            "TP": 0,
            "FP": 2,
            "FN": 0
          }
        }
      }
    }
  },
  {
    "Result": {
      "Success": false,
      "Summary": "Passed:  criteria0 (Success): 3 / 3 -> 100.00%, Failed:  criteria1 (Fail): 0 / 3 -> 0.00%"
    },
    "Stamp": {
      "System": 1705038422.7112164,
      "ROS": 1686890778.1615667
    },
    "Frame": {
      "criteria0": {
        "Filter": {
          "Distance": [0.0, 50.0]
        },
        "Ego": {
          "TransformStamped": {
            "header": {
              "stamp": {
                "sec": 1686890777,
                "nanosec": 650037504
              },
              "frame_id": "map"
            },
            "child_frame_id": "base_link",
            "transform": {
              "translation": {
                "x": 65400.00526024097,
                "y": 684.6111007932517,
                "z": 716.0405397784184
              },
              "rotation": {
                "x": -0.004605335286118828,
                "y": 0.009976225137601177,
                "z": 0.022386967655222603,
                "w": 0.9996889963874317
              }
            },
            "rotation_euler": {
              "roll": -0.008763022895681117,
              "pitch": 0.020153808279728676,
              "yaw": 0.04469207219238894
            }
          }
        },
        "FrameName": "2",
        "FrameSkip": 8,
        "PassFail": {
          "Result": {
            "Total": "Success",
            "Frame": "Success"
          },
          "Info": {
            "TP": 0,
            "FP": 0,
            "FN": 0
          }
        }
      },
      "criteria1": {
        "Filter": {
          "Distance": [50.0, 1.7976931348623157e308]
        },
        "Ego": {
          "TransformStamped": {
            "header": {
              "stamp": {
                "sec": 1686890777,
                "nanosec": 650037504
              },
              "frame_id": "map"
            },
            "child_frame_id": "base_link",
            "transform": {
              "translation": {
                "x": 65400.00526024097,
                "y": 684.6111007932517,
                "z": 716.0405397784184
              },
              "rotation": {
                "x": -0.004605335286118828,
                "y": 0.009976225137601177,
                "z": 0.022386967655222603,
                "w": 0.9996889963874317
              }
            },
            "rotation_euler": {
              "roll": -0.008763022895681117,
              "pitch": 0.020153808279728676,
              "yaw": 0.04469207219238894
            }
          }
        },
        "FrameName": "2",
        "FrameSkip": 8,
        "PassFail": {
          "Result": {
            "Total": "Fail",
            "Frame": "Fail"
          },
          "Info": {
            "TP": 0,
            "FP": 2,
            "FN": 0
          }
        }
      }
    }
  },
  {
    "Result": {
      "Success": false,
      "Summary": "Passed:  criteria0 (Success): 4 / 4 -> 100.00%, Failed:  criteria1 (Fail): 0 / 4 -> 0.00%"
    },
    "Stamp": {
      "System": 1705038423.0665712,
      "ROS": 1686890778.3440664
    },
    "Frame": {
      "criteria0": {
        "Filter": {
          "Distance": [0.0, 50.0]
        },
        "Ego": {
          "TransformStamped": {
            "header": {
              "stamp": {
                "sec": 1686890777,
                "nanosec": 850023424
              },
              "frame_id": "map"
            },
            "child_frame_id": "base_link",
            "transform": {
              "translation": {
                "x": 65400.00481367562,
                "y": 684.6110692053678,
                "z": 716.0403587764331
              },
              "rotation": {
                "x": -0.004576314099557418,
                "y": 0.009973248323340683,
                "z": 0.02238848163525196,
                "w": 0.9996891254571149
              }
            },
            "rotation_euler": {
              "roll": -0.008705087596298308,
              "pitch": 0.020146572072452726,
              "yaw": 0.04469570913476024
            }
          }
        },
        "FrameName": "4",
        "FrameSkip": 8,
        "PassFail": {
          "Result": {
            "Total": "Success",
            "Frame": "Success"
          },
          "Info": {
            "TP": 0,
            "FP": 0,
            "FN": 0
          }
        }
      },
      "criteria1": {
        "Filter": {
          "Distance": [50.0, 1.7976931348623157e308]
        },
        "Ego": {
          "TransformStamped": {
            "header": {
              "stamp": {
                "sec": 1686890777,
                "nanosec": 850023424
              },
              "frame_id": "map"
            },
            "child_frame_id": "base_link",
            "transform": {
              "translation": {
                "x": 65400.00481367562,
                "y": 684.6110692053678,
                "z": 716.0403587764331
              },
              "rotation": {
                "x": -0.004576314099557418,
                "y": 0.009973248323340683,
                "z": 0.02238848163525196,
                "w": 0.9996891254571149
              }
            },
            "rotation_euler": {
              "roll": -0.008705087596298308,
              "pitch": 0.020146572072452726,
              "yaw": 0.04469570913476024
            }
          }
        },
        "FrameName": "4",
        "FrameSkip": 8,
        "PassFail": {
          "Result": {
            "Total": "Fail",
            "Frame": "Fail"
          },
          "Info": {
            "TP": 0,
            "FP": 1,
            "FN": 0
          }
        }
      }
    }
  },
  {
    "Result": {
      "Success": false,
      "Summary": "Passed:  criteria0 (Success): 5 / 5 -> 100.00%, Failed:  criteria1 (Fail): 0 / 5 -> 0.00%"
    },
    "Stamp": {
      "System": 1705038423.3166504,
      "ROS": 1686890778.4690711
    },
    "Frame": {
      "criteria0": {
        "Filter": {
          "Distance": [0.0, 50.0]
        },
        "Ego": {
          "TransformStamped": {
            "header": {
              "stamp": {
                "sec": 1686890777,
                "nanosec": 950042880
              },
              "frame_id": "map"
            },
            "child_frame_id": "base_link",
            "transform": {
              "translation": {
                "x": 65400.00488470575,
                "y": 684.6110674235956,
                "z": 716.0406388603086
              },
              "rotation": {
                "x": -0.004574545989314534,
                "y": 0.009974539290472822,
                "z": 0.022390233649747997,
                "w": 0.9996890814308438
              }
            },
            "rotation_euler": {
              "roll": -0.008701458883216023,
              "pitch": 0.02014908969548868,
              "yaw": 0.04469924006820567
            }
          }
        },
        "FrameName": "5",
        "FrameSkip": 8,
        "PassFail": {
          "Result": {
            "Total": "Success",
            "Frame": "Success"
          },
          "Info": {
            "TP": 0,
            "FP": 0,
            "FN": 0
          }
        }
      },
      "criteria1": {
        "Filter": {
          "Distance": [50.0, 1.7976931348623157e308]
        },
        "Ego": {
          "TransformStamped": {
            "header": {
              "stamp": {
                "sec": 1686890777,
                "nanosec": 950042880
              },
              "frame_id": "map"
            },
            "child_frame_id": "base_link",
            "transform": {
              "translation": {
                "x": 65400.00488470575,
                "y": 684.6110674235956,
                "z": 716.0406388603086
              },
              "rotation": {
                "x": -0.004574545989314534,
                "y": 0.009974539290472822,
                "z": 0.022390233649747997,
                "w": 0.9996890814308438
              }
            },
            "rotation_euler": {
              "roll": -0.008701458883216023,
              "pitch": 0.02014908969548868,
              "yaw": 0.04469924006820567
            }
          }
        },
        "FrameName": "5",
        "FrameSkip": 8,
        "PassFail": {
          "Result": {
            "Total": "Fail",
            "Frame": "Fail"
          },
          "Info": {
            "TP": 0,
            "FP": 1,
            "FN": 0
          }
        }
      }
    }
  },
  {
    "Result": {
      "Success": false,
      "Summary": "Passed:  criteria0 (Success): 6 / 6 -> 100.00%, Failed:  criteria1 (Fail): 0 / 6 -> 0.00%"
    },
    "Stamp": {
      "System": 1705038423.6711042,
      "ROS": 1686890778.6465638
    },
    "Frame": {
      "criteria0": {
        "Filter": {
          "Distance": [0.0, 50.0]
        },
        "Ego": {
          "TransformStamped": {
            "header": {
              "stamp": {
                "sec": 1686890778,
                "nanosec": 150015488
              },
              "frame_id": "map"
            },
            "child_frame_id": "base_link",
            "transform": {
              "translation": {
                "x": 65400.00468571643,
                "y": 684.6110332713714,
                "z": 716.0432856814343
              },
              "rotation": {
                "x": -0.00459723382015831,
                "y": 0.009997872697393174,
                "z": 0.022399089836646277,
                "w": 0.9996885458767742
              }
            },
            "rotation_euler": {
              "roll": -0.008745612611386717,
              "pitch": 0.0201968384058462,
              "yaw": 0.044716319387941364
            }
          }
        },
        "FrameName": "7",
        "FrameSkip": 8,
        "PassFail": {
          "Result": {
            "Total": "Success",
            "Frame": "Success"
          },
          "Info": {
            "TP": 0,
            "FP": 0,
            "FN": 0
          }
        }
      },
      "criteria1": {
        "Filter": {
          "Distance": [50.0, 1.7976931348623157e308]
        },
        "Ego": {
          "TransformStamped": {
            "header": {
              "stamp": {
                "sec": 1686890778,
                "nanosec": 150015488
              },
              "frame_id": "map"
            },
            "child_frame_id": "base_link",
            "transform": {
              "translation": {
                "x": 65400.00468571643,
                "y": 684.6110332713714,
                "z": 716.0432856814343
              },
              "rotation": {
                "x": -0.00459723382015831,
                "y": 0.009997872697393174,
                "z": 0.022399089836646277,
                "w": 0.9996885458767742
              }
            },
            "rotation_euler": {
              "roll": -0.008745612611386717,
              "pitch": 0.0201968384058462,
              "yaw": 0.044716319387941364
            }
          }
        },
        "FrameName": "7",
        "FrameSkip": 8,
        "PassFail": {
          "Result": {
            "Total": "Fail",
            "Frame": "Fail"
          },
          "Info": {
            "TP": 0,
            "FP": 1,
            "FN": 0
          }
        }
      }
    }
  },
  {
    "Result": {
      "Success": false,
      "Summary": "Passed:  criteria0 (Success): 7 / 7 -> 100.00%, Failed:  criteria1 (Fail): 0 / 7 -> 0.00%"
    },
    "Stamp": {
      "System": 1705038423.9023552,
      "ROS": 1686890778.7615733
    },
    "Frame": {
      "criteria0": {
        "Filter": {
          "Distance": [0.0, 50.0]
        },
        "Ego": {
          "TransformStamped": {
            "header": {
              "stamp": {
                "sec": 1686890778,
                "nanosec": 250087680
              },
              "frame_id": "map"
            },
            "child_frame_id": "base_link",
            "transform": {
              "translation": {
                "x": 65400.00455329998,
                "y": 684.611006454502,
                "z": 716.043883165945
              },
              "rotation": {
                "x": -0.004607020330113487,
                "y": 0.010003103168310205,
                "z": 0.022401647074036062,
                "w": 0.9996883911995039
              }
            },
            "rotation_euler": {
              "roll": -0.008764899239590004,
              "pitch": 0.02020775720347624,
              "yaw": 0.04472119718851952
            }
          }
        },
        "FrameName": "8",
        "FrameSkip": 8,
        "PassFail": {
          "Result": {
            "Total": "Success",
            "Frame": "Success"
          },
          "Info": {
            "TP": 0,
            "FP": 0,
            "FN": 0
          }
        }
      },
      "criteria1": {
        "Filter": {
          "Distance": [50.0, 1.7976931348623157e308]
        },
        "Ego": {
          "TransformStamped": {
            "header": {
              "stamp": {
                "sec": 1686890778,
                "nanosec": 250087680
              },
              "frame_id": "map"
            },
            "child_frame_id": "base_link",
            "transform": {
              "translation": {
                "x": 65400.00455329998,
                "y": 684.611006454502,
                "z": 716.043883165945
              },
              "rotation": {
                "x": -0.004607020330113487,
                "y": 0.010003103168310205,
                "z": 0.022401647074036062,
                "w": 0.9996883911995039
              }
            },
            "rotation_euler": {
              "roll": -0.008764899239590004,
              "pitch": 0.02020775720347624,
              "yaw": 0.04472119718851952
            }
          }
        },
        "FrameName": "8",
        "FrameSkip": 8,
        "PassFail": {
          "Result": {
            "Total": "Fail",
            "Frame": "Fail"
          },
          "Info": {
            "TP": 0,
            "FP": 1,
            "FN": 0
          }
        }
      }
    }
  },
  {
    "Result": {
      "Success": false,
      "Summary": "Passed:  criteria0 (Success): 8 / 8 -> 100.00%, Failed:  criteria1 (Fail): 0 / 8 -> 0.00%"
    },
    "Stamp": {
      "System": 1705038424.272139,
      "ROS": 1686890778.9465609
    },
    "Frame": {
      "criteria0": {
        "Filter": {
          "Distance": [0.0, 50.0]
        },
        "Ego": {
          "TransformStamped": {
            "header": {
              "stamp": {
                "sec": 1686890778,
                "nanosec": 450003456
              },
              "frame_id": "map"
            },
            "child_frame_id": "base_link",
            "transform": {
              "translation": {
                "x": 65400.004481711585,
                "y": 684.6109469693524,
                "z": 716.0427955545565
              },
              "rotation": {
                "x": -0.004691947189151766,
                "y": 0.010015208088826315,
                "z": 0.022414744610716977,
                "w": 0.9996875814285922
              }
            },
            "rotation_euler": {
              "roll": -0.008933933950555419,
              "pitch": 0.020235876938600524,
              "yaw": 0.044745589952753864
            }
          }
        },
        "FrameName": "10",
        "FrameSkip": 8,
        "PassFail": {
          "Result": {
            "Total": "Success",
            "Frame": "Success"
          },
          "Info": {
            "TP": 0,
            "FP": 0,
            "FN": 0
          }
        }
      },
      "criteria1": {
        "Filter": {
          "Distance": [50.0, 1.7976931348623157e308]
        },
        "Ego": {
          "TransformStamped": {
            "header": {
              "stamp": {
                "sec": 1686890778,
                "nanosec": 450003456
              },
              "frame_id": "map"
            },
            "child_frame_id": "base_link",
            "transform": {
              "translation": {
                "x": 65400.004481711585,
                "y": 684.6109469693524,
                "z": 716.0427955545565
              },
              "rotation": {
                "x": -0.004691947189151766,
                "y": 0.010015208088826315,
                "z": 0.022414744610716977,
                "w": 0.9996875814285922
              }
            },
            "rotation_euler": {
              "roll": -0.008933933950555419,
              "pitch": 0.020235876938600524,
              "yaw": 0.044745589952753864
            }
          }
        },
        "FrameName": "10",
        "FrameSkip": 8,
        "PassFail": {
          "Result": {
            "Total": "Fail",
            "Frame": "Fail"
          },
          "Info": {
            "TP": 0,
            "FP": 2,
            "FN": 0
          }
        }
      }
    }
  },
  {
    "Result": {
      "Success": false,
      "Summary": "Passed:  criteria0 (Success): 9 / 9 -> 100.00%, Failed:  criteria1 (Fail): 0 / 9 -> 0.00%"
    },
    "Stamp": {
      "System": 1705038424.5062153,
      "ROS": 1686890779.0615668
    },
    "Frame": {
      "criteria0": {
        "Filter": {
          "Distance": [0.0, 50.0]
        },
        "Ego": {
          "TransformStamped": {
            "header": {
              "stamp": {
                "sec": 1686890778,
                "nanosec": 550081536
              },
              "frame_id": "map"
            },
            "child_frame_id": "base_link",
            "transform": {
              "translation": {
                "x": 65400.004251329956,
                "y": 684.6109268626332,
                "z": 716.0432307208769
              },
              "rotation": {
                "x": -0.004663144451037809,
                "y": 0.010016254740087768,
                "z": 0.02242228908639405,
                "w": 0.9996875365217557
              }
            },
            "rotation_euler": {
              "roll": -0.008876134028220468,
              "pitch": 0.020236748015812777,
              "yaw": 0.044761259028160506
            }
          }
        },
        "FrameName": "11",
        "FrameSkip": 8,
        "PassFail": {
          "Result": {
            "Total": "Success",
            "Frame": "Success"
          },
          "Info": {
            "TP": 0,
            "FP": 0,
            "FN": 0
          }
        }
      },
      "criteria1": {
        "Filter": {
          "Distance": [50.0, 1.7976931348623157e308]
        },
        "Ego": {
          "TransformStamped": {
            "header": {
              "stamp": {
                "sec": 1686890778,
                "nanosec": 550081536
              },
              "frame_id": "map"
            },
            "child_frame_id": "base_link",
            "transform": {
              "translation": {
                "x": 65400.004251329956,
                "y": 684.6109268626332,
                "z": 716.0432307208769
              },
              "rotation": {
                "x": -0.004663144451037809,
                "y": 0.010016254740087768,
                "z": 0.02242228908639405,
                "w": 0.9996875365217557
              }
            },
            "rotation_euler": {
              "roll": -0.008876134028220468,
              "pitch": 0.020236748015812777,
              "yaw": 0.044761259028160506
            }
          }
        },
        "FrameName": "11",
        "FrameSkip": 8,
        "PassFail": {
          "Result": {
            "Total": "Fail",
            "Frame": "Fail"
          },
          "Info": {
            "TP": 0,
            "FP": 2,
            "FN": 0
          }
        }
      }
    }
  },
  {
    "Result": {
      "Success": false,
      "Summary": "Passed:  criteria0 (Success): 10 / 10 -> 100.00%, Failed:  criteria1 (Fail): 0 / 10 -> 0.00%"
    },
    "Stamp": {
      "System": 1705038424.8675456,
      "ROS": 1686890779.2440844
    },
    "Frame": {
      "criteria0": {
        "Filter": {
          "Distance": [0.0, 50.0]
        },
        "Ego": {
          "TransformStamped": {
            "header": {
              "stamp": {
                "sec": 1686890778,
                "nanosec": 749985792
              },
              "frame_id": "map"
            },
            "child_frame_id": "base_link",
            "transform": {
              "translation": {
                "x": 65400.00405271804,
                "y": 684.6108900993722,
                "z": 716.0447854797719
              },
              "rotation": {
                "x": -0.00470288430719195,
                "y": 0.010030793467409671,
                "z": 0.02242691267093917,
                "w": 0.9996871008718965
              }
            },
            "rotation_euler": {
              "roll": -0.00895486491975365,
              "pitch": 0.020267639585332956,
              "yaw": 0.0447695889767843
            }
          }
        },
        "FrameName": "13",
        "FrameSkip": 8,
        "PassFail": {
          "Result": {
            "Total": "Success",
            "Frame": "Success"
          },
          "Info": {
            "TP": 0,
            "FP": 0,
            "FN": 0
          }
        }
      },
      "criteria1": {
        "Filter": {
          "Distance": [50.0, 1.7976931348623157e308]
        },
        "Ego": {
          "TransformStamped": {
            "header": {
              "stamp": {
                "sec": 1686890778,
                "nanosec": 749985792
              },
              "frame_id": "map"
            },
            "child_frame_id": "base_link",
            "transform": {
              "translation": {
                "x": 65400.00405271804,
                "y": 684.6108900993722,
                "z": 716.0447854797719
              },
              "rotation": {
                "x": -0.00470288430719195,
                "y": 0.010030793467409671,
                "z": 0.02242691267093917,
                "w": 0.9996871008718965
              }
            },
            "rotation_euler": {
              "roll": -0.00895486491975365,
              "pitch": 0.020267639585332956,
              "yaw": 0.0447695889767843
            }
          }
        },
        "FrameName": "13",
        "FrameSkip": 8,
        "PassFail": {
          "Result": {
            "Total": "Fail",
            "Frame": "Fail"
          },
          "Info": {
            "TP": 0,
            "FP": 2,
            "FN": 0
          }
        }
      }
    }
  },
  {
    "Result": {
      "Success": false,
      "Summary": "Failed:  criteria0 (Fail): 10 / 11 -> 90.91%, Failed:  criteria1 (Fail): 1 / 11 -> 9.09%"
    },
    "Stamp": {
      "System": 1705038425.090572,
      "ROS": 1686890779.3518891
    },
    "Frame": {
      "criteria0": {
        "Filter": {
          "Distance": [0.0, 50.0]
        },
        "Ego": {
          "TransformStamped": {
            "header": {
              "stamp": {
                "sec": 1686890778,
                "nanosec": 849870592
              },
              "frame_id": "map"
            },
            "child_frame_id": "base_link",
            "transform": {
              "translation": {
                "x": 65400.00385499479,
                "y": 684.6108646220132,
                "z": 716.0446244614934
              },
              "rotation": {
                "x": -0.004708980759675406,
                "y": 0.010029004855078136,
                "z": 0.022428708643411076,
                "w": 0.9996870498262997
              }
            },
            "rotation_euler": {
              "roll": -0.00896710013795253,
              "pitch": 0.02026435214465157,
              "yaw": 0.0447730732732787
            }
          }
        },
        "FrameName": "14",
        "FrameSkip": 8,
        "PassFail": {
          "Result": {
            "Total": "Fail",
            "Frame": "Fail"
          },
          "Info": {
            "TP": 0,
            "FP": 1,
            "FN": 0
          }
        }
      },
      "criteria1": {
        "Filter": {
          "Distance": [50.0, 1.7976931348623157e308]
        },
        "Ego": {
          "TransformStamped": {
            "header": {
              "stamp": {
                "sec": 1686890778,
                "nanosec": 849870592
              },
              "frame_id": "map"
            },
            "child_frame_id": "base_link",
            "transform": {
              "translation": {
                "x": 65400.00385499479,
                "y": 684.6108646220132,
                "z": 716.0446244614934
              },
              "rotation": {
                "x": -0.004708980759675406,
                "y": 0.010029004855078136,
                "z": 0.022428708643411076,
                "w": 0.9996870498262997
              }
            },
            "rotation_euler": {
              "roll": -0.00896710013795253,
              "pitch": 0.02026435214465157,
              "yaw": 0.0447730732732787
            }
          }
        },
        "FrameName": "14",
        "FrameSkip": 8,
        "PassFail": {
          "Result": {
            "Total": "Fail",
            "Frame": "Success"
          },
          "Info": {
            "TP": 0,
            "FP": 2,
            "FN": 0
          }
        }
      }
    }
  },
  {
    "Result": {
      "Success": false,
      "Summary": "Failed:  criteria0 (Fail): 10 / 12 -> 83.33%, Failed:  criteria1 (Fail): 2 / 12 -> 16.67%"
    },
    "Stamp": {
      "System": 1705038425.264495,
      "ROS": 1686890779.4415858
    },
    "Frame": {
      "criteria0": {
        "Filter": {
          "Distance": [0.0, 50.0]
        },
        "Ego": {
          "TransformStamped": {
            "header": {
              "stamp": {
                "sec": 1686890778,
                "nanosec": 949758720
              },
              "frame_id": "map"
            },
            "child_frame_id": "base_link",
            "transform": {
              "translation": {
                "x": 65400.00398340225,
                "y": 684.6108709407486,
                "z": 716.0444961771012
              },
              "rotation": {
                "x": -0.004725071274877609,
                "y": 0.01002992353058816,
                "z": 0.02242956451199937,
                "w": 0.999686945484045
              }
            },
            "rotation_euler": {
              "roll": -0.008999220091440377,
              "pitch": 0.020266917221332843,
              "yaw": 0.04477445236026213
            }
          }
        },
        "FrameName": "15",
        "FrameSkip": 8,
        "PassFail": {
          "Result": {
            "Total": "Fail",
            "Frame": "Fail"
          },
          "Info": {
            "TP": 0,
            "FP": 1,
            "FN": 0
          }
        }
      },
      "criteria1": {
        "Filter": {
          "Distance": [50.0, 1.7976931348623157e308]
        },
        "Ego": {
          "TransformStamped": {
            "header": {
              "stamp": {
                "sec": 1686890778,
                "nanosec": 949758720
              },
              "frame_id": "map"
            },
            "child_frame_id": "base_link",
            "transform": {
              "translation": {
                "x": 65400.00398340225,
                "y": 684.6108709407486,
                "z": 716.0444961771012
              },
              "rotation": {
                "x": -0.004725071274877609,
                "y": 0.01002992353058816,
                "z": 0.02242956451199937,
                "w": 0.999686945484045
              }
            },
            "rotation_euler": {
              "roll": -0.008999220091440377,
              "pitch": 0.020266917221332843,
              "yaw": 0.04477445236026213
            }
          }
        },
        "FrameName": "15",
        "FrameSkip": 8,
        "PassFail": {
          "Result": {
            "Total": "Fail",
            "Frame": "Success"
          },
          "Info": {
            "TP": 0,
            "FP": 2,
            "FN": 0
          }
        }
      }
    }
  },
  {
    "Result": {
      "Success": false,
      "Summary": "Failed:  criteria0 (Fail): 10 / 13 -> 76.92%, Failed:  criteria1 (Fail): 3 / 13 -> 23.08%"
    },
    "Stamp": {
      "System": 1705038425.5101366,
      "ROS": 1686890779.5640898
    },
    "Frame": {
      "criteria0": {
        "Filter": {
          "Distance": [0.0, 50.0]
        },
        "Ego": {
          "TransformStamped": {
            "header": {
              "stamp": {
                "sec": 1686890779,
                "nanosec": 49636608
              },
              "frame_id": "map"
            },
            "child_frame_id": "base_link",
            "transform": {
              "translation": {
                "x": 65400.004099152524,
                "y": 684.6108764770597,
                "z": 716.0456679902536
              },
              "rotation": {
                "x": -0.0047447730600887065,
                "y": 0.010035224150192968,
                "z": 0.022429857514021108,
                "w": 0.9996867923988815
              }
            },
            "rotation_euler": {
              "roll": -0.009038377949772013,
              "pitch": 0.020278401014397724,
              "yaw": 0.044774596391769096
            }
          }
        },
        "FrameName": "16",
        "FrameSkip": 8,
        "PassFail": {
          "Result": {
            "Total": "Fail",
            "Frame": "Fail"
          },
          "Info": {
            "TP": 0,
            "FP": 1,
            "FN": 0
          }
        }
      },
      "criteria1": {
        "Filter": {
          "Distance": [50.0, 1.7976931348623157e308]
        },
        "Ego": {
          "TransformStamped": {
            "header": {
              "stamp": {
                "sec": 1686890779,
                "nanosec": 49636608
              },
              "frame_id": "map"
            },
            "child_frame_id": "base_link",
            "transform": {
              "translation": {
                "x": 65400.004099152524,
                "y": 684.6108764770597,
                "z": 716.0456679902536
              },
              "rotation": {
                "x": -0.0047447730600887065,
                "y": 0.010035224150192968,
                "z": 0.022429857514021108,
                "w": 0.9996867923988815
              }
            },
            "rotation_euler": {
              "roll": -0.009038377949772013,
              "pitch": 0.020278401014397724,
              "yaw": 0.044774596391769096
            }
          }
        },
        "FrameName": "16",
        "FrameSkip": 8,
        "PassFail": {
          "Result": {
            "Total": "Fail",
            "Frame": "Success"
          },
          "Info": {
            "TP": 0,
            "FP": 2,
            "FN": 0
          }
        }
      }
    }
  },
  {
    "Result": {
      "Success": false,
      "Summary": "Failed:  criteria0 (Fail): 10 / 14 -> 71.43%, Failed:  criteria1 (Fail): 4 / 14 -> 28.57%"
    },
    "Stamp": {
      "System": 1705038425.7224605,
      "ROS": 1686890779.666597
    },
    "Frame": {
      "criteria0": {
        "Filter": {
          "Distance": [0.0, 50.0]
        },
        "Ego": {
          "TransformStamped": {
            "header": {
              "stamp": {
                "sec": 1686890779,
                "nanosec": 149546496
              },
              "frame_id": "map"
            },
            "child_frame_id": "base_link",
            "transform": {
              "translation": {
                "x": 65400.00414944549,
                "y": 684.6108796665243,
                "z": 716.0470237111127
              },
              "rotation": {
                "x": -0.004726723221195294,
                "y": 0.010052862828906694,
                "z": 0.022429488241646967,
                "w": 0.9996867089712412
              }
            },
            "rotation_euler": {
              "roll": -0.009001502161709335,
              "pitch": 0.020312859540498548,
              "yaw": 0.04477408053544646
            }
          }
        },
        "FrameName": "17",
        "FrameSkip": 8,
        "PassFail": {
          "Result": {
            "Total": "Fail",
            "Frame": "Fail"
          },
          "Info": {
            "TP": 0,
            "FP": 2,
            "FN": 0
          }
        }
      },
      "criteria1": {
        "Filter": {
          "Distance": [50.0, 1.7976931348623157e308]
        },
        "Ego": {
          "TransformStamped": {
            "header": {
              "stamp": {
                "sec": 1686890779,
                "nanosec": 149546496
              },
              "frame_id": "map"
            },
            "child_frame_id": "base_link",
            "transform": {
              "translation": {
                "x": 65400.00414944549,
                "y": 684.6108796665243,
                "z": 716.0470237111127
              },
              "rotation": {
                "x": -0.004726723221195294,
                "y": 0.010052862828906694,
                "z": 0.022429488241646967,
                "w": 0.9996867089712412
              }
            },
            "rotation_euler": {
              "roll": -0.009001502161709335,
              "pitch": 0.020312859540498548,
              "yaw": 0.04477408053544646
            }
          }
        },
        "FrameName": "17",
        "FrameSkip": 8,
        "PassFail": {
          "Result": {
            "Total": "Fail",
            "Frame": "Success"
          },
          "Info": {
            "TP": 0,
            "FP": 1,
            "FN": 0
          }
        }
      }
    }
  },
  {
    "Result": {
      "Success": false,
      "Summary": "Failed:  criteria0 (Fail): 10 / 15 -> 66.67%, Failed:  criteria1 (Fail): 5 / 15 -> 33.33%"
    },
    "Stamp": {
      "System": 1705038426.086033,
      "ROS": 1686890779.8515985
    },
    "Frame": {
      "criteria0": {
        "Filter": {
          "Distance": [0.0, 50.0]
        },
        "Ego": {
          "TransformStamped": {
            "header": {
              "stamp": {
                "sec": 1686890779,
                "nanosec": 349511680
              },
              "frame_id": "map"
            },
            "child_frame_id": "base_link",
            "transform": {
              "translation": {
                "x": 65400.00421387269,
                "y": 684.6109135616247,
                "z": 716.0430821557264
              },
              "rotation": {
                "x": -0.0047087258729837135,
                "y": 0.010014019906047581,
                "z": 0.022422535575320424,
                "w": 0.9996873397239499
              }
            },
            "rotation_euler": {
              "roll": -0.008967383691792575,
              "pitch": 0.02023432170706169,
              "yaw": 0.04476084827053028
            }
          }
        },
        "FrameName": "19",
        "FrameSkip": 8,
        "PassFail": {
          "Result": {
            "Total": "Fail",
            "Frame": "Fail"
          },
          "Info": {
            "TP": 0,
            "FP": 2,
            "FN": 0
          }
        }
      },
      "criteria1": {
        "Filter": {
          "Distance": [50.0, 1.7976931348623157e308]
        },
        "Ego": {
          "TransformStamped": {
            "header": {
              "stamp": {
                "sec": 1686890779,
                "nanosec": 349511680
              },
              "frame_id": "map"
            },
            "child_frame_id": "base_link",
            "transform": {
              "translation": {
                "x": 65400.00421387269,
                "y": 684.6109135616247,
                "z": 716.0430821557264
              },
              "rotation": {
                "x": -0.0047087258729837135,
                "y": 0.010014019906047581,
                "z": 0.022422535575320424,
                "w": 0.9996873397239499
              }
            },
            "rotation_euler": {
              "roll": -0.008967383691792575,
              "pitch": 0.02023432170706169,
              "yaw": 0.04476084827053028
            }
          }
        },
        "FrameName": "19",
        "FrameSkip": 8,
        "PassFail": {
          "Result": {
            "Total": "Fail",
            "Frame": "Success"
          },
          "Info": {
            "TP": 0,
            "FP": 1,
            "FN": 0
          }
        }
      }
    }
  },
  {
    "Result": {
      "Success": false,
      "Summary": "Failed:  criteria0 (Fail): 10 / 15 -> 66.67%, Failed:  criteria1 (Fail): 5 / 15 -> 33.33%"
    },
    "Stamp": {
      "System": 1705038434.157699,
      "ROS": 1686890781.3416226
    },
    "Frame": {
      "FinalScore": {
        "GroundTruthStatus": {
          "2b3dbc70e876f6829fb27301e27316f0": {
            "rate": {
              "TP": null,
              "FP": 1.0,
              "TN": null,
              "FN": null
            },
            "frame_nums": {
              "total": [0, 1, 2],
              "TP": [],
              "FP": [0, 1, 2],
              "TN": [],
              "FN": []
            }
          },
          "cb1040491bbcf642078c00a7a75c95f9": {
            "rate": {
              "TP": null,
              "FP": 1.0,
              "TN": null,
              "FN": null
            },
            "frame_nums": {
              "total": [0, 1, 2, 4, 5, 7, 8, 10, 11, 13, 14, 15, 16, 17, 19],
              "TP": [],
              "FP": [0, 1, 2, 4, 5, 7, 8, 10, 11, 13, 14, 15, 16, 17, 19],
              "TN": [],
              "FN": []
            }
          },
          "837029711ca9fbfd36f5dd7c59846c37": {
            "rate": {
              "TP": null,
              "FP": 1.0,
              "TN": null,
              "FN": null
            },
            "frame_nums": {
              "total": [10, 11, 13, 14, 15, 16, 17, 19],
              "TP": [],
              "FP": [10, 11, 13, 14, 15, 16, 17, 19],
              "TN": [],
              "FN": []
            }
          },
          "d363a05be6f01b25e4d21794b320fcc0": {
            "rate": {
              "TP": null,
              "FP": 1.0,
              "TN": null,
              "FN": null
            },
            "frame_nums": {
              "total": [14, 15, 16, 17, 19],
              "TP": [],
              "FP": [14, 15, 16, 17, 19],
              "TN": [],
              "FN": []
            }
          }
        },
        "Scene": {
          "TP": 0.0,
          "FP": 1.0,
          "TN": 0.0,
          "FN": 0.0
        }
      }
    }
  }
]
